{
    "validation_key": "Empa",
    "ui_label": "Swiss Federal Laboratories for Materials Science and Technology",
    "description": "",
    "acronyms": [
        "EMPA"
    ],
    "aliases": [],
    "established": 1880,
    "kind": "facility",
    "labels": [
        "Eidgenössische Materialprüfungs- und Forschungsanstalt",
        "Laboratoire fédéral d'essai des matériaux et de recherche",
        "Swiss Federal Laboratories for Materials Science and Technology"
    ],
    "location": [
        {
            "@id": "universal:location/02x681a42",
            "@type": "wcrp:location",
            "continent_code": "EU",
            "continent_name": "Europe",
            "country_code": "CH",
            "country_name": "Switzerland",
            "country_subdivision_code": "ZH",
            "country_subdivision_name": "Zurich",
            "lat": 47.39724,
            "lng": 8.61872,
            "name": "Dübendorf"
        }
    ],
    "ror": "02x681a42",
    "url": [
        "https://www.empa.ch",
        "https://en.wikipedia.org/wiki/Swiss_Federal_Laboratories_for_Materials_Science_and_Technology"
    ],
    "@context": "_context",
    "@type": [
        "wcrp:organisation",
        "esgvoc:Organisation",
        "universal"
    ],
    "@id": "empa"
}
