{
  "@context": "000_context.jsonld",
  "id": "bldep_tmax-u-hxy-u",
  "type": "known_branded_variable",
  "drs_name": "bldep_tmax-u-hxy-u",
  "cf_standard_name": "atmosphere_boundary_layer_thickness",
  "cf_units": "m",
  "variable_root_name": "bldep",
  "branding_suffix_name": "tmax-u-hxy-u",
  "long_name": "Maximum PBL Height",
  "description": [
    "maximum boundary layer height during the day (add cell_methods attribute: \"time: maximum\")"
  ],
  "data_type": "real",
  "dimensions": [
    "lon",
    "lat",
    "time"
  ],
  "coordinates": [
    "longitude",
    "latitude",
    "time"
  ],
  "cell_methods": [
    "area: mean time: maximum"
  ],
  "cell_measures": [
    "area: areacella"
  ],
  "realm": [
    "atmos"
  ],
  "region": [
    "global"
  ],
  "temporal_label": "tmax",
  "vertical_label": "u",
  "horizontal_label": "hxy",
  "area_label": "u",
  "positive_direction": ""
}
