{
  "@context": "000_context.jsonld",
  "id": "hfgeoubed_tavg-u-hxy-gis",
  "type": "known_branded_variable",
  "drs_name": "hfgeoubed_tavg-u-hxy-gis",
  "cf_standard_name": "upward_geothermal_heat_flux_at_ground_level_in_land_ice",
  "cf_units": "W m-2",
  "variable_root_name": "hfgeoubed",
  "branding_suffix_name": "tavg-u-hxy-gis",
  "long_name": "Geothermal Heat Flux Beneath Land Ice",
  "description": [
    "Geothermal Heat Flux Beneath Land Ice"
  ],
  "data_type": "real",
  "dimensions": [
    "lon",
    "lat",
    "time"
  ],
  "coordinates": [
    "longitude",
    "latitude",
    "time"
  ],
  "cell_methods": [
    "area: time: mean where grounded_ice_sheet (mask=sfgrlf)"
  ],
  "cell_measures": [
    "area: areacellg"
  ],
  "realm": [
    "landice"
  ],
  "region": [
    "greenland",
    "antarctica"
  ],
  "temporal_label": "tavg",
  "vertical_label": "u",
  "horizontal_label": "hxy",
  "area_label": "gis",
  "positive_direction": ""
}
