{
  "@context": "000_context.jsonld",
  "id": "limndiaz_tavg-u-hxy-sea",
  "type": "known_branded_variable",
  "drs_name": "limndiaz_tavg-u-hxy-sea",
  "cf_standard_name": "nitrogen_growth_limitation_of_diazotrophic_phytoplankton",
  "cf_units": "1",
  "variable_root_name": "limndiaz",
  "branding_suffix_name": "tavg-u-hxy-sea",
  "long_name": "Nitrogen Limitation of Diazotrophs",
  "description": [
    "In ocean modelling, diazotrophs are phytoplankton of the phylum cyanobacteria distinct from other phytoplankton groups in their ability to fix nitrogen gas in addition to nitrate and ammonium. Phytoplankton are algae that grow where there is sufficient light to support photosynthesis. \"Nitrogen growth limitation\" means the ratio of the growth rate of a species population in the environment (where there is a finite availability of nitrogen) to the theoretical growth rate if there were no such limit on nitrogen availability."
  ],
  "data_type": "real",
  "dimensions": [
    "lon",
    "lat",
    "time"
  ],
  "coordinates": [
    "longitude",
    "latitude",
    "time"
  ],
  "cell_methods": [
    "area: mean where sea time: mean"
  ],
  "cell_measures": [
    "area: areacello"
  ],
  "realm": [
    "ocnbgchem"
  ],
  "region": [
    "global"
  ],
  "temporal_label": "tavg",
  "vertical_label": "u",
  "horizontal_label": "hxy",
  "area_label": "sea",
  "positive_direction": ""
}
