{
  "@context": "000_context.jsonld",
  "id": "rivo_tavg-u-hxy-lnd",
  "type": "known_branded_variable",
  "drs_name": "rivo_tavg-u-hxy-lnd",
  "cf_standard_name": "outgoing_water_volume_transport_along_river_channel",
  "cf_units": "m3 s-1",
  "variable_root_name": "rivo",
  "branding_suffix_name": "tavg-u-hxy-lnd",
  "long_name": "River Discharge",
  "description": [
    "water_flux_from_upstream"
  ],
  "data_type": "real",
  "dimensions": [
    "lon",
    "lat",
    "time"
  ],
  "coordinates": [
    "longitude",
    "latitude",
    "time"
  ],
  "cell_methods": [
    "area: mean where land time: mean"
  ],
  "cell_measures": [
    "area: areacellr"
  ],
  "realm": [
    "land"
  ],
  "region": [
    "global"
  ],
  "temporal_label": "tavg",
  "vertical_label": "u",
  "horizontal_label": "hxy",
  "area_label": "lnd",
  "positive_direction": ""
}
