{
  "@context": "000_context.jsonld",
  "id": "wa_tavg-al-hxy-u",
  "type": "known_branded_variable",
  "drs_name": "wa_tavg-al-hxy-u",
  "cf_standard_name": "upward_air_velocity",
  "cf_units": "m s-1",
  "variable_root_name": "wa",
  "branding_suffix_name": "tavg-al-hxy-u",
  "long_name": "Upward Air Velocity",
  "description": [
    "A velocity is a vector quantity. \"Upward\" indicates a vector component which is positive when directed upward (negative downward). Upward air velocity is the vertical component of the 3D air velocity vector. The standard name downward_air_velocity may be used for a vector component with the opposite sign convention."
  ],
  "data_type": "real",
  "dimensions": [
    "lon",
    "lat",
    "lev",
    "time"
  ],
  "coordinates": [
    "longitude",
    "latitude",
    "alevel",
    "time"
  ],
  "cell_methods": [
    "area: time: mean"
  ],
  "cell_measures": [
    "area: areacella"
  ],
  "realm": [
    "aerosol"
  ],
  "region": [
    "global"
  ],
  "temporal_label": "tavg",
  "vertical_label": "al",
  "horizontal_label": "hxy",
  "area_label": "u",
  "positive_direction": ""
}
